ocrtest/__init__.py
ocrtest/hello.py
OCRTest-0.0.5.dist-info/LICENSE
OCRTest-0.0.5.dist-info/METADATA
OCRTest-0.0.5.dist-info/WHEEL
OCRTest-0.0.5.dist-info/top_level.txt
OCRTest-0.0.5.dist-info/RECORD
