Metadata-Version: 2.1
Name: OCRTest
Version: 0.0.5
Summary: An OCR hello package
Author: OCR Research Lab
Author-email: <vuquocminhdang@gmail.com>
Keywords: python
Classifier: Development Status :: 1 - Planning
Classifier: Intended Audience :: Developers
Classifier: Programming Language :: Python :: 3
Classifier: Operating System :: Unix
Classifier: Operating System :: MacOS :: MacOS X
Classifier: Operating System :: Microsoft :: Windows
License-File: LICENSE
